pynpoint/__init__.py
pynpoint/_version.py
pynpoint/core/__init__.py
pynpoint/core/attributes.py
pynpoint/core/dataio.py
pynpoint/core/processing.py
pynpoint/core/pypeline.py
pynpoint/processing/__init__.py
pynpoint/processing/background.py
pynpoint/processing/badpixel.py
pynpoint/processing/basic.py
pynpoint/processing/centering.py
pynpoint/processing/darkflat.py
pynpoint/processing/extract.py
pynpoint/processing/filter.py
pynpoint/processing/fluxposition.py
pynpoint/processing/frameselection.py
pynpoint/processing/limits.py
pynpoint/processing/pcabackground.py
pynpoint/processing/psfpreparation.py
pynpoint/processing/psfsubtraction.py
pynpoint/processing/resizing.py
pynpoint/processing/stacksubset.py
pynpoint/processing/timedenoising.py
pynpoint/readwrite/__init__.py
pynpoint/readwrite/attr_reading.py
pynpoint/readwrite/attr_writing.py
pynpoint/readwrite/fitsreading.py
pynpoint/readwrite/fitswriting.py
pynpoint/readwrite/hdf5reading.py
pynpoint/readwrite/hdf5writing.py
pynpoint/readwrite/nearreading.py
pynpoint/readwrite/textwriting.py
pynpoint/util/__init__.py
pynpoint/util/analysis.py
pynpoint/util/apply_func.py
pynpoint/util/attributes.py
pynpoint/util/continuous.py
pynpoint/util/image.py
pynpoint/util/limits.py
pynpoint/util/mcmc.py
pynpoint/util/module.py
pynpoint/util/multiline.py
pynpoint/util/multipca.py
pynpoint/util/multiproc.py
pynpoint/util/multistack.py
pynpoint/util/postproc.py
pynpoint/util/psf.py
pynpoint/util/remove.py
pynpoint/util/residuals.py
pynpoint/util/sdi.py
pynpoint/util/star.py
pynpoint/util/tests.py
pynpoint/util/type_aliases.py
pynpoint/util/wavelets.py
pynpoint-0.11.2.dist-info/licenses/LICENSE
pynpoint-0.11.2.dist-info/METADATA
pynpoint-0.11.2.dist-info/WHEEL
pynpoint-0.11.2.dist-info/top_level.txt
pynpoint-0.11.2.dist-info/RECORD
