Metadata-Version: 2.4
Name: pynpoint
Version: 0.11.2
Summary: Pipeline for processing and analysis of high-contrast imaging data
Author-email: Tomas Stolker <stolker@strw.leidenuniv.nl>, Markus Bonse <Markus.Bonse@eso.org>
License: GPL-3.0
Project-URL: Documentation, https://pynpoint.readthedocs.io
Project-URL: Repository, https://github.com/PynPoint/PynPoint
Project-URL: Issues, https://github.com/PynPoint/PynPoint/issues
Classifier: Programming Language :: Python :: 3.11
Classifier: Programming Language :: Python :: 3.12
Classifier: Programming Language :: Python :: 3.13
Classifier: Intended Audience :: Science/Research
Classifier: Topic :: Scientific/Engineering :: Astronomy
Requires-Python: <3.14,>=3.11
License-File: LICENSE
Requires-Dist: astropy
Requires-Dist: emcee
Requires-Dist: h5py
Requires-Dist: numba
Requires-Dist: numpy
Requires-Dist: opencv-python
Requires-Dist: photutils
Requires-Dist: PyWavelets
Requires-Dist: scikit-image
Requires-Dist: scikit-learn
Requires-Dist: scipy
Requires-Dist: statsmodels
Requires-Dist: tqdm
Requires-Dist: typeguard
Provides-Extra: docs
Requires-Dist: jupyter; extra == "docs"
Requires-Dist: nbsphinx; extra == "docs"
Requires-Dist: pandoc; extra == "docs"
Requires-Dist: sphinx; extra == "docs"
Requires-Dist: sphinx-automodapi; extra == "docs"
Requires-Dist: sphinx_book_theme; extra == "docs"
Provides-Extra: test
Requires-Dist: black; extra == "test"
Requires-Dist: flake8; extra == "test"
Requires-Dist: pooch; extra == "test"
Requires-Dist: pycodestyle; extra == "test"
Requires-Dist: pylint; extra == "test"
Requires-Dist: pytest; extra == "test"
Requires-Dist: pytest-cov; extra == "test"
Dynamic: license-file
